kodexa_spatialkit/__init__.py
kodexa_spatialkit/azure_models.py
kodexa_spatialkit/bbox_common.py
kodexa_spatialkit/table_form_common.py
kodexa_spatialkit-1.0.23b0.dist-info/LICENSE
kodexa_spatialkit-1.0.23b0.dist-info/METADATA
kodexa_spatialkit-1.0.23b0.dist-info/WHEEL
kodexa_spatialkit-1.0.23b0.dist-info/entry_points.txt
kodexa_spatialkit-1.0.23b0.dist-info/top_level.txt
kodexa_spatialkit-1.0.23b0.dist-info/RECORD
