Metadata-Version: 2.1
Name: kodexa-spatialkit
Version: 1.0.23b0
Summary: Kodexa Spatial Toolkit
Home-page: https://www.github.com/kodexa-ai/kodexa-spatialkit
Author: Kodexa
Author-email: support@kodexa.io
License: UNKNOWN
Platform: UNKNOWN
Classifier: Development Status :: 4 - Beta
Classifier: Intended Audience :: Developers
Classifier: Topic :: Software Development :: Libraries
Classifier: License :: OSI Approved :: GNU General Public License v3 or later (GPLv3+)
Classifier: Programming Language :: Python :: 3.9
License-File: LICENSE
Requires-Dist: kodexa
Requires-Dist: bbox
